pytest_open_html.py
pytest_open_html-0.1.0.dist-info/LICENSE
pytest_open_html-0.1.0.dist-info/METADATA
pytest_open_html-0.1.0.dist-info/WHEEL
pytest_open_html-0.1.0.dist-info/entry_points.txt
pytest_open_html-0.1.0.dist-info/top_level.txt
pytest_open_html-0.1.0.dist-info/RECORD
