Metadata-Version: 2.1
Name: pytest-open-html
Version: 0.1.0
Summary: Auto-open HTML reports after pytest runs
Author: Your Name
Author-email: your@email.com
License: MIT
Classifier: Framework :: Pytest
Classifier: Programming Language :: Python :: 3
Classifier: License :: OSI Approved :: MIT License
License-File: LICENSE
Requires-Dist: pytest>=6.0
Requires-Dist: pytest-html
